Chromosome/__init__.py
Chromosome/darwin.py
Chromosome/genome.py
Chromosome/target.py
Chromosome-0.1.1.dist-info/LICENSE
Chromosome-0.1.1.dist-info/METADATA
Chromosome-0.1.1.dist-info/WHEEL
Chromosome-0.1.1.dist-info/top_level.txt
Chromosome-0.1.1.dist-info/RECORD
